fakerabbit/__init__.py
fakerabbit/fakerabbit.py
tests/__init__.py
tests/basetest.py
tests/modeltest.py
tests/test_create_objects.py
fakerabbit-1.0.0.dist-info/LICENSE.txt
fakerabbit-1.0.0.dist-info/METADATA
fakerabbit-1.0.0.dist-info/WHEEL
fakerabbit-1.0.0.dist-info/top_level.txt
fakerabbit-1.0.0.dist-info/RECORD
