Metadata-Version: 2.1
Name: fakerabbit
Version: 1.0.0
Summary: A simple lib to make fake objects using SQLAlchemy
Home-page: https://github.com/fariias/fake_rabbit.git
Author: Junior Farias
Author-email: josenildoaf@gmail.com
License: MIT
Download-URL: https://github.com/fariias/fake_rabbit.git
Keywords: Factory,Fake,SQLAlchemy,Tests
Platform: UNKNOWN
Requires-Dist: SQLAlchemy
